Metadata-Version: 2.4
Name: physo
Version: 1.1.11
Summary: Physical Symbolic Optimization
Home-page: https://github.com/WassimTenachi/PhySO
Author: Wassim Tenachi
Author-email: w.tenachi@gmail.com
License: MIT
Project-URL: Source, https://github.com/WassimTenachi/PhySO
Project-URL: Documentation, https://physo.readthedocs.io/
Project-URL: Bug Reports, https://github.com/WassimTenachi/PhySO/issues
Keywords: physical symbolic optimization,symbolic optimization,machine learning,reinforcement learning,deep learning,physics,symbolic regression,equation discovery
Classifier: Development Status :: 4 - Beta
Classifier: License :: OSI Approved :: MIT License
Classifier: Programming Language :: Python :: 3
Classifier: Topic :: Scientific/Engineering
Classifier: Topic :: Scientific/Engineering :: Physics
Classifier: Topic :: Scientific/Engineering :: Artificial Intelligence
Classifier: Intended Audience :: Science/Research
Requires-Python: >=3.8
License-File: LICENSE
Requires-Dist: torch>=1.11.0
Requires-Dist: numpy
Requires-Dist: sympy
Requires-Dist: pandas
Requires-Dist: matplotlib
Requires-Dist: scikit-learn
Dynamic: author
Dynamic: author-email
Dynamic: classifier
Dynamic: description
Dynamic: description-content-type
Dynamic: home-page
Dynamic: keywords
Dynamic: license
Dynamic: license-file
Dynamic: project-url
Dynamic: requires-dist
Dynamic: requires-python
Dynamic: summary
